Metadata-Version: 2.1
Name: uds-lib-test
Version: 0.1.3
Summary: Lib for UDS API
Home-page: UNKNOWN
Author-email: s@uds.app
License: UNKNOWN
Platform: UNKNOWN
